{
	"name": "German 1/10",
	"typableSides": [0, 1],
	"sides": ["German", "English"],
	"cards": [
		{"sides": ["ich", "I"]},
		{"sides": ["seine", "his"]},
		{"sides": ["dass", "that"]},
		{"sides": ["er", "he"]},
		{"sides": ["war", "was"]},
		{"sides": ["für", "for"]},
		{"sides": ["auf", "on"]},
		{"sides": ["sind", "are"]},
		{"sides": ["mit", "with"]},
		{"sides": ["sie", "they"]},
		{"sides": ["haben", "have"]},
		{"sides": ["dies", "this"]},
		{"sides": ["aus", "from"]},
		{"sides": ["durch", "by"]},
		{"sides": ["heiß", "hot"]},
		{"sides": ["das Wort", "the word"]},
		{"sides": ["aber", "but"]},
		{"sides": ["was", "what"]},
		{"sides": ["einige", "some"]},
		{"sides": ["ist", "is"]},
		{"sides": ["es", "it"]},
		{"sides": ["Sie", "you"]},
		{"sides": ["oder", "or"]},
		{"sides": ["hatte", "had"]},
		{"sides": ["die", "the"]},
		{"sides": ["von", "of"]},
		{"sides": ["zu", "to"]},
		{"sides": ["und", "and"]},
		{"sides": ["ein", "a"]},
		{"sides": ["wir", "we"]},
		{"sides": ["können", "can"]},
		{"sides": ["andere", "other"]},
		{"sides": ["waren", "were"]},
		{"sides": ["tun", "do"]},
		{"sides": ["ihre", "their"]},
		{"sides": ["Zeit", "time"]},
		{"sides": ["werden", "will"]},
		{"sides": ["wie [h]", "how"]},
		{"sides": ["sagte", "said"]},
		{"sides": ["jeder", "each"]},
		{"sides": ["sagen", "tell"]},
		{"sides": ["tut", "does"]},
		{"sides": ["Satz", "set"]},
		{"sides": ["drei", "three"]},
		{"sides": ["wollen", "want"]},
		{"sides": ["Luft", "air"]},
		{"sides": ["gut", "well"]},
		{"sides": ["auch", "also"]},
		{"sides": ["spielen", "play"]},
		{"sides": ["klein", "small"]},
		{"sides": ["das Ende", "the end"]},
		{"sides": ["setzen", "put"]},
		{"sides": ["Zuhause", "home"]},
		{"sides": ["lesen", "read"]},
		{"sides": ["Hafen", "port"]},
		{"sides": ["groß", "large"]},
		{"sides": ["buchstabieren", "spell"]},
		{"sides": ["hinzufügen", "add"]},
		{"sides": ["Lande", "land"]},
		{"sides": ["hier", "here"]},
		{"sides": ["muss", "must"]},
		{"sides": ["groß", "big"]},
		{"sides": ["hoch", "high"]},
		{"sides": ["folgen", "follow"]},
		{"sides": ["Akt", "act"]},
		{"sides": ["warum", "why"]},
		{"sides": ["fragen", "ask"]},
		{"sides": ["Männer", "men"]},
		{"sides": ["Veränderung", "change"]},
		{"sides": ["ging", "went"]},
		{"sides": ["Licht", "light"]},
		{"sides": ["Art", "kind"]},
		{"sides": ["müssen", "need"]},
		{"sides": ["Haus", "house"]},
		{"sides": ["Bild", "picture"]},
		{"sides": ["versuchen", "try"]},
		{"sides": ["uns", "us"]},
		{"sides": ["wieder", "again"]},
		{"sides": ["Tier", "animal"]},
		{"sides": ["Punkt", "point"]},
		{"sides": ["Mutter", "mother"]},
		{"sides": ["Welt", "world"]},
		{"sides": ["in der Nähe von", "near"]},
		{"sides": ["bauen", "build"]},
		{"sides": ["selbst", "self"]},
		{"sides": ["Erde", "earth"]},
		{"sides": ["Vater", "father"]},
		{"sides": ["die Kuh", "the cow"]},
		{"sides": ["der Stier", "the bull"]},
		{"sides": ["das Pferd", "the horse"]},
		{"sides": ["die Stute", "the mare"]},
		{"sides": ["der Esel", "the donkey"]},
		{"sides": ["das Schwein", "the pig"]},
		{"sides": ["das Schaf", "the sheep"]},
		{"sides": ["die Ziege", "the goat"]},
		{"sides": ["die Henne", "the chicken"]},
		{"sides": ["der Hahn", "the rooster"]},
		{"sides": ["die Ente", "the duck"]},
		{"sides": ["die Gans", "the goose"]},
		{"sides": ["der Affe", "the monkey"]},
		{"sides": ["die Antilope", "the antelope"]},
		{"sides": ["der Bär", "the bear"]},
		{"sides": ["das Eichhörnchen", "the squirrel"]},
		{"sides": ["der Elch", "the moose"]},
		{"sides": ["der Elefant", "the elephant"]},
		{"sides": ["der Fischotter", "the otter"]},
		{"sides": ["die Fledermaus", "the bat"]},
		{"sides": ["das Frettchen", "the ferret"]},
		{"sides": ["der Fuchs", "the fox"]},
		{"sides": ["die Giraffe", "the giraffe"]},
		{"sides": ["der Hase", "the hare"]},
		{"sides": ["der Hirsch", "the deer"]},
		{"sides": ["das Kamel", "the camel"]},
		{"sides": ["das Kaninchen", "the rabbit"]},
		{"sides": ["das Nashorn", "the rhinoceros"]},
		{"sides": ["die Maus", "the mouse"]},
		{"sides": ["der Löwe", "the lion"]},
		{"sides": ["der Luchs", "the lynx"]},
		{"sides": ["der Panther", "the panther"]},
		{"sides": ["das Rentier", "the reindeer"]},
		{"sides": ["das Schnabeltier", "the platypus"]},
		{"sides": ["der Siebenschläfer", "the dormouse"]},
		{"sides": ["der Steppenwolf", "the coyote"]},
		{"sides": ["der Tiger", "the tiger"]},
		{"sides": ["der Waschbär", "the raccoon"]},
		{"sides": ["das Wiesel", "the weasel"]},
		{"sides": ["das Wildschwein", "the boar"]},
		{"sides": ["der Wolf", "the wolf"]},
		{"sides": ["das Zebra", "the zebra"]},
		{"sides": ["rot","red"]},
		{"sides": ["orange","orange"]},
		{"sides": ["gelb","yellow"]},
		{"sides": ["grün","green"]},
		{"sides": ["blau","blue"]},
		{"sides": ["lila","purple"]},
		{"sides": ["rosa","pink"]},
		{"sides": ["braun","brown"]},
		{"sides": ["schwarz","black"]},
		{"sides": ["weiß","white"]},
		{"sides": ["null","zero"]},
		{"sides": ["eins","one"]},
		{"sides": ["zwei","two"]},
		{"sides": ["drei","three"]},
		{"sides": ["vier","four"]},
		{"sides": ["fünf","five"]},
		{"sides": ["sechs","six"]},
		{"sides": ["sieben","seven"]},
		{"sides": ["acht","eight"]},
		{"sides": ["neun","nine"]},
		{"sides": ["zehn","ten"]},
		{"sides": ["elf","eleven"]},
		{"sides": ["zwölf","twelve"]},
		{"sides": ["dreizehn","thirteen"]},
		{"sides": ["vierzehn","fourteen"]},
		{"sides": ["fünfzehn","fifteen"]},
		{"sides": ["sechzehn","sixteen"]},
		{"sides": ["siebzehn","seventeen"]},
		{"sides": ["achtzehn","eighteen"]},
		{"sides": ["neunzehn","nineteen"]},
		{"sides": ["zwanzig","twenty"]},
		{"sides": ["dreißig","thirty"]},
		{"sides": ["vierzig","forty"]},
		{"sides": ["fünfzig","fifty"]},
		{"sides": ["sechzig","sixty"]},
		{"sides": ["siebzig","seventy"]},
		{"sides": ["achtzig","eighty"]},
		{"sides": ["neunzig","ninety"]},
		{"sides": ["einhundert","one hundred"]},
		{"sides": ["die Vorspeise","the starter"]},
		{"sides": ["die Hauptspeise","the main dish"]},
		{"sides": ["die Beilage","the side dish"]},
		{"sides": ["die Nachspeise","the dessert"]},
		{"sides": ["das Fleisch","the meat"]},
		{"sides": ["das Rindfleisch","the beef"]},
		{"sides": ["das Schweinefleisch","the pork"]},
		{"sides": ["das Geflügel","the poultry"]},
		{"sides": ["der Fisch","the fish"]},
		{"sides": ["die Meeresfrüchte","the seafood"]},
		{"sides": ["das Gemüse","the vegetables"]},
		{"sides": ["das Obst","the fruit"]},
		{"sides": ["die Kartoffel","the potato"]},
		{"sides": ["der Käse","the cheese"]},
		{"sides": ["das Brot","the bread"]},
		{"sides": ["das Getränk","the drink"]},
		{"sides": ["das Wasser","the water"]},
		{"sides": ["der Saft","the juice"]},
		{"sides": ["der Kaffee","the coffee"]},
		{"sides": ["die Milch","the milk"]},
		{"sides": ["der Wein","the wine"]},
		{"sides": ["das Bier","the beer"]},
		{"sides": ["der Tee","the tea"]},
		{"sides": ["aufhören", "to stop"]}
	]
}
